devtools_text_reverser/__init__.py
devtools_text_reverser-1.0.1.dist-info/METADATA
devtools_text_reverser-1.0.1.dist-info/WHEEL
devtools_text_reverser-1.0.1.dist-info/top_level.txt
devtools_text_reverser-1.0.1.dist-info/RECORD
