Metadata-Version: 2.1
Name: devtools_text_reverser
Version: 1.0.1
Summary: Text reverser
Home-page: https://devtools.at/tools/text-reverser
Author: DevTools.at
Author-email: hello@devtools.at
Project-URL: Homepage, https://devtools.at/tools/text-reverser
Project-URL: Repository, https://github.com/devtools-at/text-reverser
Classifier: Development Status :: 4 - Beta
Classifier: Intended Audience :: Developers
Classifier: License :: OSI Approved :: MIT License
Classifier: Programming Language :: Python :: 3
Requires-Python: >=3.8
